cleanio/CleanIO.py
cleanio/Selftext.txt
cleanio/__init__.py
cleanio-0.1.4.dist-info/LICENSE.txt
cleanio-0.1.4.dist-info/METADATA
cleanio-0.1.4.dist-info/WHEEL
cleanio-0.1.4.dist-info/RECORD
