Metadata-Version: 2.1
Name: CleanIO
Version: 0.1.4
Summary: Simple IO eliminating the boilerplate.
Home-page: https://github.com/deeppunster/CleanIO/
License: MIT
Keywords: IO,yield
Author: Travis Risner
Author-email: cleanio@punmyword.com
Requires-Python: >=3.8
Classifier: License :: OSI Approved :: MIT License
Classifier: Operating System :: OS Independent
Classifier: Programming Language :: Python :: 3
Classifier: Programming Language :: Python :: 3.8
Classifier: Programming Language :: Python :: 3.9
Classifier: Programming Language :: Python :: 3.10
Classifier: Programming Language :: Python :: 3.11
Classifier: Programming Language :: Python :: 3.12
Project-URL: Issues, https://github.com/deeppunster/CleanIO/issues
Project-URL: Repository, https://github.com/deeppunster/CleanIO/
